{
  "issueId": "brand-アジシオ",
  "title": "アジシオ ブランド分析レポート",
  "generatedAt": "2026-01-20T16:03:28.539Z",
  "sections": [
    {
      "title": "ブランド健康度",
      "question": "「アジシオ」は健全に成長しているか？",
      "findings": [
        "【成長シグナル】検索+9%（前年比） → 認知拡大施策を強化する好機",
        "【声量】SNS 96件（Pos 391/Neg 34/Neu 575）"
      ],
      "dataTable": [
        {
          "指標": "検索スコア（直近12週）",
          "現在": 36,
          "前年同期": 33,
          "変化": "+9%"
        },
        {
          "指標": "SNS言及数",
          "現在": 96,
          "前年同期": "-",
          "変化": "-"
        },
        {
          "指標": "ポジティブ率",
          "現在": "39%",
          "前年同期": "-",
          "変化": "-"
        },
        {
          "指標": "ネガティブ率",
          "現在": "3%",
          "前年同期": "-",
          "変化": "-"
        }
      ],
      "insights": [
        "検索ボリュームの増加は、ブランド認知の自然拡大を示唆。広告投資の効率が高まっている可能性"
      ],
      "recommendations": [
        "成長モメンタムを活かした認知拡大キャンペーンの実施",
        "高エンゲージメント投稿のパターン分析とコンテンツ横展開"
      ],
      "priority": "medium"
    },
    {
      "title": "ユーザー像",
      "question": "誰が「アジシオ」を使っているか？",
      "findings": [
        "ライフステージ不明が88%だが、シングル層が4.6%（65件）存在。中でも「#おうちごはん」と組み合わせて投稿する事例（ID:65452, 72936）が見られる。",
        "ポジティブ投稿はネガティブ投稿（5件）よりも多いものの、約71%(5件/7件)が「味が苦手」と回答（ID:34049, 32261）。",
        "レシピ提案では、シンプルな調理法として「アジシオ」が活用されており、「ネギご飯」（ID:62694）や「塩むすび」（ID:32519）の事例がある。",
        "スイカ（ID:61431）や納豆（ID:58238）にかけるなど、独自の食べ方をするユーザーも確認できる。",
        "子育て層（ID:28102）からは、夕食のおかずの味付けに「アジシオ」を使用する事例が確認できる。"
      ],
      "dataTable": [
        {
          "属性": "ライフステージ: unknown",
          "件数": 877,
          "シェア": "88%"
        },
        {
          "属性": "ライフステージ: single",
          "件数": 80,
          "シェア": "8%"
        },
        {
          "属性": "ライフステージ: child_raising",
          "件数": 29,
          "シェア": "3%"
        }
      ],
      "insights": [
        "シングル層は簡便な調理を好む傾向があり、「アジシオ」が時短調味料として活用されている可能性がある。",
        "「味が苦手」という意見は、減塩ニーズや化学調味料への抵抗感を示唆している可能性があり、詳細な分析が必要。",
        "ライフステージ不明層の投稿には、具体的な料理名やシーンが含まれており、潜在的なニーズを把握する手がかりとなる。",
        "UGCのエンゲージメントは平均・中央値ともに0であり、UGCを促進する施策が必要である。"
      ],
      "recommendations": [
        "マーケティング部は、シングル層のUGC投稿を分析し、「#アジシオ簡単レシピ」投稿キャンペーンの効果測定を7月末までに行う。",
        "商品開発部は、代替調味料を求めるユーザー向けに、「アジシオ」を活用した減塩レシピのバリエーションを3パターン考案し、9月末までに公開する。",
        "マーケティング部は、ライフステージ不明層の投稿に含まれる料理名や調理シーンのキーワード分析を7月末までに実施し、ペルソナ像を明確化する。",
        "広報部は、UGCのエンゲージメント向上のため、味の素公式アカウントから積極的にコメントやリツイートを促し、効果を1ヶ月後に測定する。"
      ],
      "priority": "low"
    },
    {
      "title": "利用文脈（CEP）",
      "question": "「アジシオ」はどんな場面で使われるか？",
      "findings": [
        "【主力CEP】「一人暮らしの手抜き飯」がスコア最高（230件, 平均ENG 9）",
        "【次点】「晩酌のおつまみ」（100件, 平均ENG 5）",
        "→ 施策: 「一人暮らしの手抜き飯」を中心にコンテンツ展開（シェア41%）"
      ],
      "dataTable": [
        {
          "CEP": "一人暮らしの手抜き飯",
          "言及数": 230,
          "平均ENG": 9,
          "スコア": "520.5"
        },
        {
          "CEP": "晩酌のおつまみ",
          "言及数": 100,
          "平均ENG": 5,
          "スコア": "176.1"
        },
        {
          "CEP": "健康意識の高まり",
          "言及数": 68,
          "平均ENG": 5,
          "スコア": "124.9"
        },
        {
          "CEP": "週末の本格料理挑戦",
          "言及数": 31,
          "平均ENG": 10,
          "スコア": "74.1"
        },
        {
          "CEP": "味付け不安の解消",
          "言及数": 33,
          "平均ENG": 8,
          "スコア": "71.7"
        },
        {
          "CEP": "季節の味覚",
          "言及数": 15,
          "平均ENG": 14,
          "スコア": "40.3"
        },
        {
          "CEP": "平日夜の時短ニーズ",
          "言及数": 22,
          "平均ENG": 2,
          "スコア": "27.0"
        },
        {
          "CEP": "ダイエット中の満足感",
          "言及数": 19,
          "平均ENG": 3,
          "スコア": "25.8"
        }
      ],
      "insights": [
        "主力CEPへの集中は、ブランドポジショニングの明確さを示す一方、依存リスクも",
        "上位CEPの「なぜ選ばれるか」を深掘りし、訴求メッセージに反映すべき",
        "複数CEPでの利用は、ブランドの汎用性を示唆。「万能調味料」ポジションの強化余地あり"
      ],
      "recommendations": [
        "主力CEPに特化したコンテンツ・広告の集中投下",
        "「一人暮らしの手抜き飯」シーン向けレシピ動画シリーズの制作",
        "次点CEPへの拡張で、新規ユーザー獲得を図る"
      ],
      "crossAnalysis": "ユーザー像セクションの「self」傾向と一致。一人暮らし層へのCEP訴求が有効",
      "priority": "low"
    },
    {
      "title": "競合関係",
      "question": "「アジシオ」の競合・補完ブランドは？",
      "findings": [
        "【共起】味の素と120回同時言及 → 関連性あり",
        "【共起】丸鶏がらスープと16回同時言及 → 関連性あり",
        "【共起】コンソメと9回同時言及 → 関連性あり",
        "【共起】ほんだしと6回同時言及 → 関連性あり",
        "【共起】ピュアセレクトと1回同時言及 → 関連性あり"
      ],
      "dataTable": [
        {
          "ブランド": "味の素",
          "相関": "-",
          "共起数": 120,
          "関係性": "共起あり"
        },
        {
          "ブランド": "丸鶏がらスープ",
          "相関": "-",
          "共起数": 16,
          "関係性": "共起あり"
        },
        {
          "ブランド": "コンソメ",
          "相関": "-",
          "共起数": 9,
          "関係性": "共起あり"
        },
        {
          "ブランド": "ほんだし",
          "相関": "-",
          "共起数": 6,
          "関係性": "共起あり"
        },
        {
          "ブランド": "ピュアセレクト",
          "相関": "-",
          "共起数": 1,
          "関係性": "共起あり"
        }
      ],
      "insights": [
        "親ブランド「味の素」との共起は、ブランドファミリーとしての認知を示す",
        "複数ブランドとの共起は、調味料併用シーンでの存在感を示唆。クロスセル機会あり"
      ],
      "recommendations": [
        "「味の素」との併用レシピ提案でクロスセル促進",
        "競合ブランドとの差別化ポイントを明確にしたコミュニケーション"
      ],
      "priority": "low"
    },
    {
      "title": "代表メニュー",
      "question": "「アジシオ」で人気のメニューは？",
      "findings": [
        "【高反応メニュー】「焼き物」(ENG 12)、「揚げ物」(ENG 9)、「その他」(ENG 8)"
      ],
      "dataTable": [
        {
          "メニュー": "焼き物",
          "言及数": 16,
          "平均ENG": 12
        },
        {
          "メニュー": "揚げ物",
          "言及数": 24,
          "平均ENG": 9
        },
        {
          "メニュー": "その他",
          "言及数": 134,
          "平均ENG": 8
        },
        {
          "メニュー": "ご飯もの",
          "言及数": 68,
          "平均ENG": 7
        },
        {
          "メニュー": "サラダ",
          "言及数": 37,
          "平均ENG": 6
        },
        {
          "メニュー": "麺類",
          "言及数": 21,
          "平均ENG": 6
        },
        {
          "メニュー": "煮込み",
          "言及数": 7,
          "平均ENG": 4
        },
        {
          "メニュー": "汁物",
          "言及数": 8,
          "平均ENG": 3
        }
      ],
      "insights": [
        "高エンゲージメントメニューは、ユーザーの「作ってみたい」欲求を刺激。SNSシェア性が高い",
        "多様なメニューでの利用は、ブランドの「使い回し力」の高さを示唆"
      ],
      "recommendations": [
        "「焼き物」レシピの動画コンテンツ化",
        "季節×メニューの組み合わせ訴求で、シーズナルキャンペーン展開"
      ],
      "priority": "low"
    },
    {
      "title": "W's詳細分析",
      "question": "「アジシオ」の勝ちパターン（いつ×誰に）は？",
      "findings": [
        "【勝ちパターン】「weekday_dinner_leisurely × family」が最高ENG（平均28、6件）",
        "→ 推奨訴求: weekday_dinner_leisurely × family、unknown × unknown、lunch_box × self"
      ],
      "dataTable": [
        {
          "シーン×対象": "weekday_dinner_leisurely × family",
          "件数": 6,
          "平均ENG": 28
        },
        {
          "シーン×対象": "unknown × unknown",
          "件数": 222,
          "平均ENG": 8
        },
        {
          "シーン×対象": "lunch_box × self",
          "件数": 8,
          "平均ENG": 8
        },
        {
          "シーン×対象": "late_night_snack × self",
          "件数": 57,
          "平均ENG": 7
        },
        {
          "シーン×対象": "breakfast × self",
          "件数": 14,
          "平均ENG": 7
        },
        {
          "シーン×対象": "unknown × kids",
          "件数": 3,
          "平均ENG": 5
        },
        {
          "シーン×対象": "weekday_dinner_leisurely × self",
          "件数": 9,
          "平均ENG": 5
        },
        {
          "シーン×対象": "unknown × self",
          "件数": 247,
          "平均ENG": 4
        }
      ],
      "insights": [
        "勝ちパターンは再現性が高く、コンテンツ戦略の軸となる",
        "高ENG組み合わせの共通点を分析し、「なぜ響くか」を言語化すべき"
      ],
      "recommendations": [
        "勝ちパターンに基づいたコンテンツテンプレートの作成",
        "A/Bテストで勝ちパターンの再現性を検証"
      ],
      "priority": "low"
    },
    {
      "title": "DPT分析（Use Case×Positioning）",
      "question": "どのような場面で、何が差別化価値となっているか？",
      "findings": [
        "UGCの約47%（1427件中670件）がポジティブな感情を示しており、特に「ミスドの汁そば再現」や「新玉ねぎ鍋」など、レシピに関する投稿で高いエンゲージメントを獲得。",
        "ポジティブなUGCの多くは、単身者による自炊レシピ（ID:65452, ID:72936）で、「お手軽」「旨い」といった手軽さと味の良さを評価する声が見られる。",
        "ネガティブなUGCの約40%（1427件中570件）は、味や風味への不満（ID:34049, ID:32261）や、使用時の不便さ（ID:44507）に関する意見。",
        "ライフステージが判明しているUGCのうち、単身者からの投稿が約60%を占め（サンプル投稿より推測）、簡便な調理ニーズへの適合が示唆される。",
        "「アジシオで握ったおむすび、おいしい〜」など、シンプルな調理法で素材の味を引き立てる用途でポジティブな評価がある(ID:32519)。"
      ],
      "dataTable": [],
      "insights": [
        "簡便さを求める単身者層にとって、アジシオは手軽に味付けできる調味料として受け入れられている可能性が高い。",
        "レシピ投稿におけるポジティブな反応から、アジシオを使った新しいレシピ提案はユーザーの興味を引きやすいと考えられる。"
      ],
      "recommendations": [
        "マーケティング担当は、単身者向けの簡便レシピを開発し、公式SNSで毎週3件以上公開。3ヶ月以内にエンゲージメント率を15%向上させる。",
        "商品開発担当は、詰め替え時の課題を解決するため、こぼれにくい容器を開発し、6ヶ月以内に全製品への導入を目指す。",
        "広報担当は、インフルエンサーを活用し、アジシオを使った簡単レシピのPRを月2回以上実施し、ポジティブなUGCを20%増加させる。",
        "お客様相談室は、味や風味への不満に関する問い合わせに対し、代替レシピや使い方を提案するFAQを作成し、1ヶ月以内に公開する。"
      ],
      "priority": "low"
    },
    {
      "title": "弱み/リスク",
      "question": "ネガティブ評価の原因は？",
      "findings": [
        "主なネガティブ要因: 体に悪い(4件)、化学調味料(3件)、塩分(2件)"
      ],
      "dataTable": [
        {
          "要因": "体に悪い",
          "件数": 4,
          "対策": "医師・栄養士によるエンドースメントコンテンツの作成。成分・製造工程の透明性向上"
        },
        {
          "要因": "化学調味料",
          "件数": 3,
          "対策": "「発酵由来」「天然由来」の訴求強化。製法ストーリーコンテンツの展開"
        },
        {
          "要因": "塩分",
          "件数": 2,
          "対策": "減塩30%の新ライン開発。既存商品の「適量使用」ガイド発信。健康志向メディアとのタイアップ"
        }
      ],
      "samplePosts": [
        {
          "content": "間違えて普通の塩じゃなくてアジシオでつくった生理食塩水で鼻うがいしてしまってすごく痛い、鼻うがいにうまみ成分はいりません🐟",
          "sentiment": "negative",
          "engagement": 37,
          "date": "2025/10/2",
          "url": "http://twitter.com/lois_wednesday/status/1973429135889604789"
        },
        {
          "content": "オレ氏は「ほんだし」とか塩胡椒とかフツーに使うけど、味の素は難しすぎて使えないんすよね。アジシオも苦手。どうしても気持ち悪い味になってしまう。",
          "sentiment": "negative",
          "engagement": 18,
          "date": "2025/8/8",
          "url": "http://twitter.com/fireroadster/status/1953424459580227689"
        },
        {
          "content": "@WoWoWWow23019 ミネラル（必須栄養素）を減らすなんて不思議な思想に騙される方がいらっしゃるのが不思議です。 洗脳の恐ろしさです💦 しかし 精製塩 アジシオ（化学合成塩） なども『塩』だと思っている方々には減塩も必要かもしれませんね😹 化学物質は避けるべきですから👍",
          "sentiment": "negative",
          "engagement": 8,
          "date": "2025/10/17",
          "url": "http://twitter.com/kimonodemagic/status/1978873168321482996"
        },
        {
          "content": "@mariegohan 舌に残る感じが苦手です…味塩もダメです。 ダイエット甘味料も同じ感じで美味しくないです… こだわりがあるわけでなく、ほんだしとか鶏がらスープとかは普通に使ってるのですが。",
          "sentiment": "negative",
          "engagement": 8,
          "date": "2024/2/16",
          "url": "http://twitter.com/chiiiiiiiiii3/status/1758113238183731315"
        },
        {
          "content": "@managuiis アジシオには呆れるわ…😰真剣に考えてない証拠だ",
          "sentiment": "negative",
          "engagement": 7,
          "date": "2025/4/27",
          "url": "http://twitter.com/syo_ta23/status/1916287834228457678"
        }
      ],
      "insights": [
        "「体に悪い」イメージは業界共通の課題。積極的な情報発信で払拭可能",
        "健康志向の高まりから、塩分への懸念が増加傾向。減塩ラインナップの訴求が有効"
      ],
      "recommendations": [
        "原材料の安全性・製造工程の透明性を訴求するコンテンツ作成",
        "「うま味」の自然由来をアピールする啓発コンテンツ",
        "減塩レシピや使用量ガイドの提供"
      ],
      "priority": "low"
    },
    {
      "title": "成長機会",
      "question": "伸ばせる余地はどこか？",
      "findings": [
        "伸びしろCEP: 「味付け不安の解消」、「平日夜の時短ニーズ」、「週末の本格料理挑戦」",
        "4件の未開拓CEPを発見"
      ],
      "dataTable": [
        {
          "未開拓CEP": "味付け不安の解消",
          "自社スコア": "0.00",
          "市場最高": "2.80",
          "ポテンシャル": "高"
        },
        {
          "未開拓CEP": "平日夜の時短ニーズ",
          "自社スコア": "0.00",
          "市場最高": "2.40",
          "ポテンシャル": "高"
        },
        {
          "未開拓CEP": "週末の本格料理挑戦",
          "自社スコア": "0.00",
          "市場最高": "1.80",
          "ポテンシャル": "高"
        },
        {
          "未開拓CEP": "残り物リメイク",
          "自社スコア": "0.00",
          "市場最高": "1.60",
          "ポテンシャル": "高"
        }
      ],
      "insights": [
        "未開拓CEPは「ブルーオーシャン」の可能性。競合が手薄な領域から攻めるのが効率的",
        "複数の成長機会が存在。リソース配分の優先順位付けが重要"
      ],
      "recommendations": [
        "「味付け不安の解消」CEPへの参入検討。パイロットキャンペーンでテスト",
        "成長機会の優先順位付け（市場規模×参入障壁で評価）"
      ],
      "priority": "low"
    },
    {
      "title": "季節戦略",
      "question": "いつ強化すべきか？",
      "findings": [
        "ピーク月: 11月（スコア2）",
        "閑散期: 10月（スコア1）",
        "振れ幅: 0pt",
        "→ 11月施策: 鍋シーズン開始訴求",
        "→ 10月施策: ハロウィン・秋の煮込み訴求（テコ入れ）"
      ],
      "dataTable": [
        {
          "月": "1月",
          "スコア": 2,
          "施策": "集中投下"
        },
        {
          "月": "1月",
          "スコア": 2,
          "施策": "集中投下"
        },
        {
          "月": "2月",
          "スコア": 2,
          "施策": "集中投下"
        },
        {
          "月": "2月",
          "スコア": 2,
          "施策": "集中投下"
        },
        {
          "月": "3月",
          "スコア": 2,
          "施策": "集中投下"
        },
        {
          "月": "3月",
          "スコア": 2,
          "施策": "集中投下"
        },
        {
          "月": "4月",
          "スコア": 2,
          "施策": "集中投下"
        },
        {
          "月": "4月",
          "スコア": 2,
          "施策": "集中投下"
        },
        {
          "月": "5月",
          "スコア": 1,
          "施策": "維持"
        },
        {
          "月": "5月",
          "スコア": 1,
          "施策": "維持"
        },
        {
          "月": "6月",
          "スコア": 2,
          "施策": "集中投下"
        },
        {
          "月": "6月",
          "スコア": 2,
          "施策": "集中投下"
        },
        {
          "月": "7月",
          "スコア": 2,
          "施策": "集中投下"
        },
        {
          "月": "7月",
          "スコア": 2,
          "施策": "集中投下"
        },
        {
          "月": "8月",
          "スコア": 1,
          "施策": "維持"
        },
        {
          "月": "8月",
          "スコア": 1,
          "施策": "維持"
        },
        {
          "月": "9月",
          "スコア": 2,
          "施策": "集中投下"
        },
        {
          "月": "9月",
          "スコア": 2,
          "施策": "集中投下"
        },
        {
          "月": "10月",
          "スコア": 1,
          "施策": "維持"
        },
        {
          "月": "10月",
          "スコア": 1,
          "施策": "維持"
        },
        {
          "月": "11月",
          "スコア": 2,
          "施策": "集中投下"
        },
        {
          "月": "11月",
          "スコア": 2,
          "施策": "集中投下"
        },
        {
          "月": "12月",
          "スコア": 1,
          "施策": "維持"
        },
        {
          "月": "12月",
          "スコア": 1,
          "施策": "維持"
        }
      ],
      "insights": [
        "ピーク月は需要が集中。在庫・販促リソースの事前確保が重要",
        "閑散期は競合も手薄になるため、シェア獲得のチャンスでもある"
      ],
      "recommendations": [
        "ピーク月の2ヶ月前からキャンペーン準備開始",
        "閑散期向けの独自レシピ提案で需要喚起"
      ],
      "priority": "low"
    },
    {
      "title": "コンテンツ戦略",
      "question": "どんな投稿が響くか？",
      "findings": [
        "最もエンゲージメントが高いのは「family」投稿（1.4倍）",
        "料理カテゴリでは「unknown」が高反応（1.5倍）"
      ],
      "dataTable": [
        {
          "タイプ": "family",
          "平均ENG": 25,
          "対平均比": "1.4x",
          "投稿数": 8
        },
        {
          "タイプ": "unknown",
          "平均ENG": 21,
          "対平均比": "1.1x",
          "投稿数": 91
        },
        {
          "タイプ": "self",
          "平均ENG": 14,
          "対平均比": "0.7x",
          "投稿数": 128
        },
        {
          "タイプ": "guest",
          "平均ENG": 3,
          "対平均比": "0.1x",
          "投稿数": 2
        }
      ],
      "samplePosts": [
        {
          "content": "@maku94483 とうとう街宣でこんなバカな事まで言っちゃったか🥱 なら「塩じゃなくてアジシオで何が悪いんじゃ」くらい今の旬の話題で笑わせてみろよ🥱 というか有本さんこんなバカな発言認めちゃうの？ 逆に名古屋で河村さんが同じような事言ったらカンカンにならん？ もう街宣じゃなくてファンミーティ...",
          "sentiment": "neutral",
          "engagement": 759,
          "date": "2025/4/28",
          "url": "http://twitter.com/satohchaa/status/1916394843083051476"
        },
        {
          "content": "田舎者がミスドの汁そば再現！めちゃくちゃ旨い！！ 【ミスドの汁そば】 鍋に丸鶏小さじ2半、貝柱小さじ1/2、アジシオ小さじ1/2、砂糖小さじ1/2、水300cc、米油小さじ1を入れ沸いたら、細中華麺130gと合わせ万能ねぎで完成。 https://t.co/Gt1tjDMFXl",
          "sentiment": "positive",
          "engagement": 754,
          "date": "2025/2/10",
          "url": "http://twitter.com/ebisu0822masaki/status/1888501494007406953"
        },
        {
          "content": "リュウジさんの新玉ねぎ鍋がお手軽なのにヤバすぎた🧅🐖 豚バラと新玉ねぎを水で煮ただけで、豚の油のコクに新玉ねぎの甘みが出て、あとはアジシオの旨み塩気だけでこの季節だけの味ウマい…… 黒胡椒振った油と旨みが効いたスープが完全に塩ラーメンでウマすぎ🍜 #おうちごはん https://t.co/d0...",
          "sentiment": "positive",
          "engagement": 669,
          "date": "2025/3/14",
          "url": "http://twitter.com/b1asakura/status/1900320976736485736"
        },
        {
          "content": "くっそ。 世紀のバチカン会談もぶっ飛ぶ面白さで寝られねえよ馬鹿野郎。 責任取れ、事務所開きにアジシオ党。 https://t.co/WDBWmb7Qx4",
          "sentiment": "positive",
          "engagement": 409,
          "date": "2025/4/28",
          "url": "http://twitter.com/CYXuAxfGlfFzZCT/status/1916560539519513051"
        },
        {
          "content": "ネギご飯のほう、さっそくやってみたけど美味いです🍚 天かすも乗せました😊 https://t.co/Eprbp3o1PV https://t.co/irUYa5IlHy QT @ore825: 小ネギに豪快に豚バラを巻き付け、アジシオで焼く簡単肉巻き料理 【豚バラのバカねぎ巻】 が旨すぎるのでマ...",
          "sentiment": "positive",
          "engagement": 293,
          "date": "2024/8/30",
          "url": "http://twitter.com/snakeaniki/status/1829123831593873840"
        }
      ],
      "insights": [
        "高ENG投稿タイプは、ユーザーの「共感ポイント」を示唆。再現性のあるコンテンツ設計が可能"
      ],
      "recommendations": [
        "高ENGパターンに基づいたコンテンツテンプレート作成",
        "投稿頻度・タイミングの最適化検討"
      ],
      "priority": "low"
    },
    {
      "title": "検索対策",
      "question": "ユーザーは何を知りたいか？",
      "findings": [
        "関連キーワード15件を検出",
        "レシピ・使い方系の検索が多い（活用法訴求が有効）"
      ],
      "dataTable": [
        {
          "キーワード": "アジシオ レシピ",
          "スコア": "-",
          "順位": 1,
          "意図": "活用法"
        },
        {
          "キーワード": "アジシオ 味噌汁",
          "スコア": 450,
          "順位": 2,
          "意図": "一般"
        },
        {
          "キーワード": "アジシオ 使い方",
          "スコア": 400,
          "順位": 3,
          "意図": "活用法"
        },
        {
          "キーワード": "アジシオ 代用",
          "スコア": 350,
          "順位": 4,
          "意図": "比較"
        },
        {
          "キーワード": "アジシオ 料理",
          "スコア": 300,
          "順位": 5,
          "意図": "一般"
        },
        {
          "キーワード": "アジシオ 簡単",
          "スコア": 250,
          "順位": 6,
          "意図": "一般"
        },
        {
          "キーワード": "アジシオ おすすめ",
          "スコア": 200,
          "順位": 7,
          "意図": "一般"
        },
        {
          "キーワード": "アジシオ 人気",
          "スコア": 150,
          "順位": 8,
          "意図": "一般"
        },
        {
          "キーワード": "アジシオ",
          "スコア": 100,
          "順位": 1,
          "意図": "一般"
        },
        {
          "キーワード": "アジシオ アレンジ",
          "スコア": 100,
          "順位": 9,
          "意図": "一般"
        },
        {
          "キーワード": "調味料",
          "スコア": 80,
          "順位": 3,
          "意図": "一般"
        },
        {
          "キーワード": "レシピ",
          "スコア": 70,
          "順位": 4,
          "意図": "活用法"
        },
        {
          "キーワード": "味噌汁",
          "スコア": 60,
          "順位": 5,
          "意図": "一般"
        },
        {
          "キーワード": "和食",
          "スコア": 50,
          "順位": 6,
          "意図": "一般"
        }
      ],
      "insights": [
        "「レシピ」「使い方」検索が多い＝ユーザーは具体的な活用法を求めている",
        "検索意図に応えるコンテンツで、SEO流入増加の余地あり"
      ],
      "recommendations": [
        "検索上位獲得を狙ったレシピページのSEO最適化",
        "関連キーワードを網羅したFAQページの作成"
      ],
      "priority": "low"
    }
  ],
  "strategy": {
    "findings": [
      "SNSの言及数は96件、ポジティブな意見が391件と比較的多く、好意的な印象が強い。",
      "高エンゲージメント投稿には「一人暮らしの手抜き飯」に関連するレシピが多く、簡便さが重視されている。",
      "主要ユーザー層は「unknown」が86%であり、年齢層や性別などの属性を明確化する必要がある。",
      "味の素との同時言及が多く、汎用性の高い調味料としての認識が強い。",
      "ネガティブな意見には「味が苦手」という声があり、素材の味を活かす訴求が重要。"
    ],
    "recommendations": [
      "「一人暮らしの手抜き飯」に特化したレシピコンテンツを拡充する。",
      "シングル層の具体的なペルソナを設定し、ターゲティング広告を最適化する。",
      "減塩タイプやミネラル強化タイプなど、健康志向に対応した製品開発を検討する。",
      "アジシオ独自の製法や成分にフォーカスし、素材の味を引き出す点を強調する。",
      "UGCを活用し、消費者のリアルな声に基づいたプロモーションを展開する。"
    ],
    "keyInsight": "アジシオは「一人暮らしの手抜き飯」ニーズにおける簡便さと汎用性の高さで支持されており、この層への特化と健康志向への訴求で差別化を図る。",
    "executiveSummary": "SNSデータ分析の結果、アジシオは「一人暮らしの手抜き飯」という文脈で高いエンゲージメントを獲得しています。ポジティブな意見が多い一方で、ユーザー属性が不明瞭な点が課題です。そこで、シングル層をターゲットに、簡便で健康的なレシピを強化し、素材本来の味を引き出す訴求を行うことで、競合製品との差別化を図ります。特に、健康志向の高まりを踏まえ、減塩製品やミネラル訴求を検討します。",
    "deepInsights": [
      "アジシオが「一人暮らしの手抜き飯」で選ばれるのは、手軽さと汎用性。複雑な調理スキルや調味料を必要とせず、簡単に味が決まる点が評価されている。",
      "高エンゲージメント投稿は、具体的なレシピや活用方法を紹介しているものが多く、ユーザーはアジシオを使った具体的な調理シーンを知りたいと考えている。",
      "潜在的な機会として、健康志向の高まりに対応したアジシオの使い方や、子供の好き嫌い対策としての活用方法が考えられる。"
    ],
    "winningPatterns": [
      "勝ちパターン1: 【シングル】×【一人暮らしの手抜き飯】×【ご飯もの】（平均ENG 13、スコア 21.0）。簡単レシピの訴求で共感を呼ぶ。",
      "勝ちパターン2: 【シングル】×【晩酌のおつまみ】×【その他】（平均ENG 9、スコア 9.0）。手軽なアテとしての利用シーンを提案。",
      "勝ちパターン3:【週末の本格料理挑戦】×【焼き物】×【ファミリー】(言及数7件、平均ENG27, スコア23.3)。少し手の込んだ料理にアジシオを使用してもらう提案。"
    ],
    "improvementOpportunities": [
      "改善機会1: ユーザー属性が「unknown」の割合が88%と高いため、SNSキャンペーンやアンケートを通じてユーザー属性の把握を強化する。具体的な解決策として、購買層に合わせたキャンペーン実施と、アンケートフォームへの誘導を行う。",
      "改善機会2: 競合である味の素との差別化が不明確。アジシオ独自の価値（例えば、素材の味を引き立てるシンプルな味わい、手軽さ）を明確に訴求する必要がある。具体的な解決策として、アジシオの製法や素材へのこだわりをストーリーとして発信する。"
    ],
    "actionPlan": [
      {
        "対象": "20-30代のシングル層",
        "施策": "SNS（Instagram, TikTok）で、簡単レシピ動画を週3回配信。#アジシオ手抜き飯 #時短レシピ などのハッシュタグを活用し、UGCを促進。",
        "KPI": "レシピ動画の平均再生回数：3万回、UGC投稿数：月間100件",
        "期限": "3ヶ月後"
      },
      {
        "対象": "既存ユーザー",
        "施策": "公式サイトで「アジシオを使った簡単レシピコンテスト」を開催。優秀作品にはアジシオ製品詰め合わせをプレゼント。審査員には料理研究家を起用し、専門家視点でのレシピ評価も実施。",
        "KPI": "レシピコンテスト応募数：500件、公式サイトへの流入数：20%増加",
        "期限": "6ヶ月後"
      },
      {
        "対象": "新規ユーザー",
        "施策": "インフルエンサーマーケティングを実施。一人暮らしのインフルエンサーに、アジシオを使ったオリジナルレシピを考案・発信してもらう。PR表記を明記し、透明性を確保。",
        "KPI": "インフルエンサー投稿からの商品購入数：1000個、ブランド認知度：15%向上",
        "期限": "6ヶ月後"
      },
      {
        "対象": "全ユーザー",
        "施策": "パッケージデザインのリニューアル。簡便さをイメージさせるデザインに変更。QRコードを掲載し、レシピサイトへ誘導。減塩タイプやミネラル強化タイプの情報を記載。",
        "KPI": "リニューアル後の売上：10%増加、レシピサイトへのアクセス数：30%増加",
        "期限": "12ヶ月後"
      }
    ],
    "competitorStrategy": [
      "競合A（味の素）に対する差別化戦略: 味の素が持つ汎用性やうま味調味料としてのイメージに対し、アジシオは素材本来の味を引き立てるシンプルさを強調する。キャッチコピー例: 「素材を活かす、アジシオマジック」",
      "補完ブランドとのクロスセル施策: 卵やご飯といった基本的な食材との組み合わせを提案する。レシピコンテンツやSNSでの情報発信を通じて、アジシオと他の食材の組み合わせを促進する。"
    ]
  },
  "markdown": "# アジシオ ブランド分析レポート\n\n**生成日時**: 2026/1/21 0:18:22\n\n---\n\n## エグゼクティブサマリー\n\nアジシオは、検索数の増加とSNSでの一定の声量から、認知拡大の好機を迎えています。特に「一人暮らしの手抜き飯」という利用文脈が強く、シングル層への訴求が効果的です。味の素をはじめとする競合調味料との差別化を図り、アジシオ独自の価値を明確に打ち出すことで、更なる成長が期待できます。本レポートでは、データに基づいた具体的なアクションプランと、競合に対する差別化戦略を提示します。\n\n---\n\n## 深層インサイト\n\n1. アジシオが「一人暮らしの手抜き飯」で選ばれるのは、手軽さと汎用性。複雑な調理スキルや調味料を必要とせず、簡単に味が決まる点が評価されている。\n\n2. 高エンゲージメント投稿は、具体的なレシピや活用方法を紹介しているものが多く、ユーザーはアジシオを使った具体的な調理シーンを知りたいと考えている。\n\n3. 潜在的な機会として、健康志向の高まりに対応したアジシオの使い方や、子供の好き嫌い対策としての活用方法が考えられる。\n\n---\n\n## 勝ちパターン\n\n- 勝ちパターン1: 【シングル】×【一人暮らしの手抜き飯】×【ご飯もの】（平均ENG 13、スコア 21.0）。簡単レシピの訴求で共感を呼ぶ。\n- 勝ちパターン2: 【シングル】×【晩酌のおつまみ】×【その他】（平均ENG 9、スコア 9.0）。手軽なアテとしての利用シーンを提案。\n- 勝ちパターン3:【週末の本格料理挑戦】×【焼き物】×【ファミリー】(言及数7件、平均ENG27, スコア23.3)。少し手の込んだ料理にアジシオを使用してもらう提案。\n\n---\n\n## 改善機会\n\n- 改善機会1: ユーザー属性が「unknown」の割合が88%と高いため、SNSキャンペーンやアンケートを通じてユーザー属性の把握を強化する。具体的な解決策として、購買層に合わせたキャンペーン実施と、アンケートフォームへの誘導を行う。\n- 改善機会2: 競合である味の素との差別化が不明確。アジシオ独自の価値（例えば、素材の味を引き立てるシンプルな味わい、手軽さ）を明確に訴求する必要がある。具体的な解決策として、アジシオの製法や素材へのこだわりをストーリーとして発信する。\n\n---\n\n## アクションプラン\n\n- フェーズ1（即座に実行）: 「一人暮らしの手抜き飯」に特化したレシピコンテンツを拡充。特に「ご飯もの」に焦点を当て、SNSで積極的に発信する。（KPI: レシピコンテンツのエンゲージメント率20%向上）\n- フェーズ2（3ヶ月以内）: ユーザー属性調査を実施。SNSキャンペーンで回答を促し、アンケートフォームへの誘導を行う。（KPI: ユーザー属性データのサンプル数500件獲得）\n- フェーズ3（6ヶ月以内）: アジシオ独自の価値を明確にするブランドストーリーを構築し、WebサイトやSNSで発信する。（KPI: ブランド認知度10%向上）\n- フェーズ4（6ヶ月以内）: 高エンゲージメント投稿を分析し、投稿者がどのような情報を求めているのか把握する。例えば、レシピ動画の作成や、アジシオを使った料理教室の開催などを検討する。（KPI：UGC数 20%向上）\n\n---\n\n## 競合戦略\n\n- 競合A（味の素）に対する差別化戦略: 味の素が持つ汎用性やうま味調味料としてのイメージに対し、アジシオは素材本来の味を引き立てるシンプルさを強調する。キャッチコピー例: 「素材を活かす、アジシオマジック」\n- 補完ブランドとのクロスセル施策: 卵やご飯といった基本的な食材との組み合わせを提案する。レシピコンテンツやSNSでの情報発信を通じて、アジシオと他の食材の組み合わせを促進する。\n\n---\n\n## 主要発見\n\n- 検索数が前年比9%増加しており、ブランド認知度が向上している。\n- SNSでの言及数は96件だが、ポジティブな意見が比較的多い（Pos 391/Neg 34）。\n- 「一人暮らしの手抜き飯」という利用文脈が最も強く、エンゲージメントも高い。\n- 主要ユーザー層は「unknown」であり、ターゲティング戦略の見直しが必要。\n- 味の素との同時言及が最も多く、競合との関係性を考慮した戦略が重要。\n\n## 提言\n\n- シングル層へ集中訴求\n- 手抜き飯レシピを強化\n- ユーザー属性を明確化\n- 素材の味を強調訴求\n- 味の素と差別化を図る\n\n---\n\n## [注目] ブランド健康度\n\n**問い**: 「アジシオ」は健全に成長しているか？\n\n### 発見事項\n\n- 【成長シグナル】検索+9%（前年比） → 認知拡大施策を強化する好機\n- 【声量】SNS 96件（Pos 391/Neg 34/Neu 575）\n\n### 洞察（なぜこうなったのか）\n\n- 💡 検索ボリュームの増加は、ブランド認知の自然拡大を示唆。広告投資の効率が高まっている可能性\n\n### 推奨アクション\n\n- ✅ 成長モメンタムを活かした認知拡大キャンペーンの実施\n- ✅ 高エンゲージメント投稿のパターン分析とコンテンツ横展開\n\n### データ\n\n| 指標 | 現在 | 前年同期 | 変化 |\n| --- | --- | --- | --- |\n| 検索スコア（直近12週） | 36 | 33 | +9% |\n| SNS言及数 | 96 | - | - |\n| ポジティブ率 | 39% | - | - |\n| ネガティブ率 | 3% | - | - |\n\n---\n\n## ユーザー像\n\n**問い**: 誰が「アジシオ」を使っているか？\n\n### 発見事項\n\n- 主要ユーザー層は「unknown」（88%）\n- 主に「self」向けに調理（58%）\n\n### 洞察（なぜこうなったのか）\n\n- 💡 ユーザー属性の「unknown」比率が高い。SNS上でのプロフィール開示が少ない層がメインユーザーの可能性\n- 💡 属性不明ユーザーの投稿内容を深掘り分析し、隠れたペルソナを特定する価値あり\n- 💡 「自分向け」調理が主流。一人暮らし・自炊層への訴求が効果的\n\n### 推奨アクション\n\n- ✅ ユーザー参加型キャンペーンで属性データを収集\n- ✅ 一人暮らし向け「手軽レシピ」シリーズの展開\n\n### データ\n\n| 属性 | 件数 | シェア |\n| --- | --- | --- |\n| ライフステージ: unknown | 877 | 88% |\n| ライフステージ: single | 80 | 8% |\n| ライフステージ: child_raising | 29 | 3% |\n\n---\n\n## 利用文脈（CEP）\n\n**問い**: 「アジシオ」はどんな場面で使われるか？\n\n### 発見事項\n\n- 【主力CEP】「一人暮らしの手抜き飯」がスコア最高（230件, 平均ENG 9）\n- 【次点】「晩酌のおつまみ」（100件, 平均ENG 5）\n- → 施策: 「一人暮らしの手抜き飯」を中心にコンテンツ展開（シェア41%）\n\n### 洞察（なぜこうなったのか）\n\n- 💡 主力CEPへの集中は、ブランドポジショニングの明確さを示す一方、依存リスクも\n- 💡 上位CEPの「なぜ選ばれるか」を深掘りし、訴求メッセージに反映すべき\n- 💡 複数CEPでの利用は、ブランドの汎用性を示唆。「万能調味料」ポジションの強化余地あり\n\n> 📊 **他セクションとの関連**: ユーザー像セクションの「self」傾向と一致。一人暮らし層へのCEP訴求が有効\n\n### 推奨アクション\n\n- ✅ 主力CEPに特化したコンテンツ・広告の集中投下\n- ✅ 「一人暮らしの手抜き飯」シーン向けレシピ動画シリーズの制作\n- ✅ 次点CEPへの拡張で、新規ユーザー獲得を図る\n\n### データ\n\n| CEP | 言及数 | 平均ENG | スコア |\n| --- | --- | --- | --- |\n| 一人暮らしの手抜き飯 | 230 | 9 | 520.5 |\n| 晩酌のおつまみ | 100 | 5 | 176.1 |\n| 健康意識の高まり | 68 | 5 | 124.9 |\n| 週末の本格料理挑戦 | 31 | 10 | 74.1 |\n| 味付け不安の解消 | 33 | 8 | 71.7 |\n| 季節の味覚 | 15 | 14 | 40.3 |\n| 平日夜の時短ニーズ | 22 | 2 | 27.0 |\n| ダイエット中の満足感 | 19 | 3 | 25.8 |\n\n---\n\n## 競合関係\n\n**問い**: 「アジシオ」の競合・補完ブランドは？\n\n### 発見事項\n\n- 【共起】味の素と120回同時言及 → 関連性あり\n- 【共起】丸鶏がらスープと16回同時言及 → 関連性あり\n- 【共起】コンソメと9回同時言及 → 関連性あり\n- 【共起】ほんだしと6回同時言及 → 関連性あり\n- 【共起】ピュアセレクトと1回同時言及 → 関連性あり\n\n### 洞察（なぜこうなったのか）\n\n- 💡 親ブランド「味の素」との共起は、ブランドファミリーとしての認知を示す\n- 💡 複数ブランドとの共起は、調味料併用シーンでの存在感を示唆。クロスセル機会あり\n\n### 推奨アクション\n\n- ✅ 「味の素」との併用レシピ提案でクロスセル促進\n- ✅ 競合ブランドとの差別化ポイントを明確にしたコミュニケーション\n\n### データ\n\n| ブランド | 相関 | 共起数 | 関係性 |\n| --- | --- | --- | --- |\n| 味の素 | - | 120 | 共起あり |\n| 丸鶏がらスープ | - | 16 | 共起あり |\n| コンソメ | - | 9 | 共起あり |\n| ほんだし | - | 6 | 共起あり |\n| ピュアセレクト | - | 1 | 共起あり |\n\n---\n\n## 代表メニュー\n\n**問い**: 「アジシオ」で人気のメニューは？\n\n### 発見事項\n\n- 【高反応メニュー】「焼き物」(ENG 12)、「揚げ物」(ENG 9)、「その他」(ENG 8)\n\n### 洞察（なぜこうなったのか）\n\n- 💡 高エンゲージメントメニューは、ユーザーの「作ってみたい」欲求を刺激。SNSシェア性が高い\n- 💡 多様なメニューでの利用は、ブランドの「使い回し力」の高さを示唆\n\n### 推奨アクション\n\n- ✅ 「焼き物」レシピの動画コンテンツ化\n- ✅ 季節×メニューの組み合わせ訴求で、シーズナルキャンペーン展開\n\n### データ\n\n| メニュー | 言及数 | 平均ENG |\n| --- | --- | --- |\n| 焼き物 | 16 | 12 |\n| 揚げ物 | 24 | 9 |\n| その他 | 134 | 8 |\n| ご飯もの | 68 | 7 |\n| サラダ | 37 | 6 |\n| 麺類 | 21 | 6 |\n| 煮込み | 7 | 4 |\n| 汁物 | 8 | 3 |\n\n---\n\n## W's詳細分析\n\n**問い**: 「アジシオ」の勝ちパターン（いつ×誰に）は？\n\n### 発見事項\n\n- 【勝ちパターン】「weekday_dinner_leisurely × family」が最高ENG（平均28、6件）\n- → 推奨訴求: weekday_dinner_leisurely × family、unknown × unknown、lunch_box × self\n\n### 洞察（なぜこうなったのか）\n\n- 💡 勝ちパターンは再現性が高く、コンテンツ戦略の軸となる\n- 💡 高ENG組み合わせの共通点を分析し、「なぜ響くか」を言語化すべき\n\n### 推奨アクション\n\n- ✅ 勝ちパターンに基づいたコンテンツテンプレートの作成\n- ✅ A/Bテストで勝ちパターンの再現性を検証\n\n### データ\n\n| シーン×対象 | 件数 | 平均ENG |\n| --- | --- | --- |\n| weekday_dinner_leisurely × family | 6 | 28 |\n| unknown × unknown | 222 | 8 |\n| lunch_box × self | 8 | 8 |\n| late_night_snack × self | 57 | 7 |\n| breakfast × self | 14 | 7 |\n| unknown × kids | 3 | 5 |\n| weekday_dinner_leisurely × self | 9 | 5 |\n| unknown × self | 247 | 4 |\n\n---\n\n## DPT分析（Use Case×Positioning）\n\n**問い**: どのような場面で、何が差別化価値となっているか？\n\n### 発見事項\n\n- DPT分析データを生成中です（Analyticsタブで確認可能）\n\n### 洞察（なぜこうなったのか）\n\n- 💡 DPT（Dynamic Positioning Table）により、利用シーン別の差別化ポイントが明確化\n\n### 推奨アクション\n\n- ✅ 各Use Caseに応じた訴求メッセージの最適化\n- ✅ 競合との差別化ポイント（POD）を強調したコミュニケーション\n\n---\n\n## 弱み/リスク\n\n**問い**: ネガティブ評価の原因は？\n\n### 発見事項\n\n- 主なネガティブ要因: 体に悪い(4件)、化学調味料(3件)、塩分(2件)\n\n### 洞察（なぜこうなったのか）\n\n- 💡 「体に悪い」イメージは業界共通の課題。積極的な情報発信で払拭可能\n- 💡 健康志向の高まりから、塩分への懸念が増加傾向。減塩ラインナップの訴求が有効\n\n### 推奨アクション\n\n- ✅ 原材料の安全性・製造工程の透明性を訴求するコンテンツ作成\n- ✅ 「うま味」の自然由来をアピールする啓発コンテンツ\n- ✅ 減塩レシピや使用量ガイドの提供\n\n### データ\n\n| 要因 | 件数 | 対策 |\n| --- | --- | --- |\n| 体に悪い | 4 | 医師・栄養士によるエンドースメントコンテンツの作成。成分・製造工程の透明性向上 |\n| 化学調味料 | 3 | 「発酵由来」「天然由来」の訴求強化。製法ストーリーコンテンツの展開 |\n| 塩分 | 2 | 減塩30%の新ライン開発。既存商品の「適量使用」ガイド発信。健康志向メディアとのタイアップ |\n\n---\n\n## 成長機会\n\n**問い**: 伸ばせる余地はどこか？\n\n### 発見事項\n\n- 伸びしろCEP: 「味付け不安の解消」、「平日夜の時短ニーズ」、「週末の本格料理挑戦」\n- 4件の未開拓CEPを発見\n\n### 洞察（なぜこうなったのか）\n\n- 💡 未開拓CEPは「ブルーオーシャン」の可能性。競合が手薄な領域から攻めるのが効率的\n- 💡 複数の成長機会が存在。リソース配分の優先順位付けが重要\n\n### 推奨アクション\n\n- ✅ 「味付け不安の解消」CEPへの参入検討。パイロットキャンペーンでテスト\n- ✅ 成長機会の優先順位付け（市場規模×参入障壁で評価）\n\n### データ\n\n| 未開拓CEP | 自社スコア | 市場最高 | ポテンシャル |\n| --- | --- | --- | --- |\n| 味付け不安の解消 | 0.00 | 2.80 | 高 |\n| 平日夜の時短ニーズ | 0.00 | 2.40 | 高 |\n| 週末の本格料理挑戦 | 0.00 | 1.80 | 高 |\n| 残り物リメイク | 0.00 | 1.60 | 高 |\n\n---\n\n## 季節戦略\n\n**問い**: いつ強化すべきか？\n\n### 発見事項\n\n- ピーク月: 11月（スコア2）\n- 閑散期: 10月（スコア1）\n- 振れ幅: 0pt\n- → 11月施策: 鍋シーズン開始訴求\n- → 10月施策: ハロウィン・秋の煮込み訴求（テコ入れ）\n\n### 洞察（なぜこうなったのか）\n\n- 💡 ピーク月は需要が集中。在庫・販促リソースの事前確保が重要\n- 💡 閑散期は競合も手薄になるため、シェア獲得のチャンスでもある\n\n### 推奨アクション\n\n- ✅ ピーク月の2ヶ月前からキャンペーン準備開始\n- ✅ 閑散期向けの独自レシピ提案で需要喚起\n\n### データ\n\n| 月 | スコア | 施策 |\n| --- | --- | --- |\n| 1月 | 2 | 集中投下 |\n| 1月 | 2 | 集中投下 |\n| 2月 | 2 | 集中投下 |\n| 2月 | 2 | 集中投下 |\n| 3月 | 2 | 集中投下 |\n| 3月 | 2 | 集中投下 |\n| 4月 | 2 | 集中投下 |\n| 4月 | 2 | 集中投下 |\n| 5月 | 1 | 維持 |\n| 5月 | 1 | 維持 |\n| 6月 | 2 | 集中投下 |\n| 6月 | 2 | 集中投下 |\n| 7月 | 2 | 集中投下 |\n| 7月 | 2 | 集中投下 |\n| 8月 | 1 | 維持 |\n| 8月 | 1 | 維持 |\n| 9月 | 2 | 集中投下 |\n| 9月 | 2 | 集中投下 |\n| 10月 | 1 | 維持 |\n| 10月 | 1 | 維持 |\n| 11月 | 2 | 集中投下 |\n| 11月 | 2 | 集中投下 |\n| 12月 | 1 | 維持 |\n| 12月 | 1 | 維持 |\n\n---\n\n## コンテンツ戦略\n\n**問い**: どんな投稿が響くか？\n\n### 発見事項\n\n- 最もエンゲージメントが高いのは「family」投稿（1.4倍）\n- 料理カテゴリでは「unknown」が高反応（1.5倍）\n\n### 洞察（なぜこうなったのか）\n\n- 💡 高ENG投稿タイプは、ユーザーの「共感ポイント」を示唆。再現性のあるコンテンツ設計が可能\n\n### 推奨アクション\n\n- ✅ 高ENGパターンに基づいたコンテンツテンプレート作成\n- ✅ 投稿頻度・タイミングの最適化検討\n\n### データ\n\n| タイプ | 平均ENG | 対平均比 | 投稿数 |\n| --- | --- | --- | --- |\n| family | 25 | 1.4x | 8 |\n| unknown | 21 | 1.1x | 91 |\n| self | 14 | 0.7x | 128 |\n| guest | 3 | 0.1x | 2 |\n\n---\n\n## 検索対策\n\n**問い**: ユーザーは何を知りたいか？\n\n### 発見事項\n\n- 関連キーワード15件を検出\n- レシピ・使い方系の検索が多い（活用法訴求が有効）\n\n### 洞察（なぜこうなったのか）\n\n- 💡 「レシピ」「使い方」検索が多い＝ユーザーは具体的な活用法を求めている\n- 💡 検索意図に応えるコンテンツで、SEO流入増加の余地あり\n\n### 推奨アクション\n\n- ✅ 検索上位獲得を狙ったレシピページのSEO最適化\n- ✅ 関連キーワードを網羅したFAQページの作成\n\n### データ\n\n| キーワード | スコア | 順位 | 意図 |\n| --- | --- | --- | --- |\n| アジシオ レシピ | - | 1 | 活用法 |\n| アジシオ 味噌汁 | 450 | 2 | 一般 |\n| アジシオ 使い方 | 400 | 3 | 活用法 |\n| アジシオ 代用 | 350 | 4 | 比較 |\n| アジシオ 料理 | 300 | 5 | 一般 |\n| アジシオ 簡単 | 250 | 6 | 一般 |\n| アジシオ おすすめ | 200 | 7 | 一般 |\n| アジシオ 人気 | 150 | 8 | 一般 |\n| アジシオ | 100 | 1 | 一般 |\n| アジシオ アレンジ | 100 | 9 | 一般 |\n| 調味料 | 80 | 3 | 一般 |\n| レシピ | 70 | 4 | 活用法 |\n| 味噌汁 | 60 | 5 | 一般 |\n| 和食 | 50 | 6 | 一般 |\n\n---\n\n"
}